koobro/__init__.py
koobro/base.py
koobro/date_time.py
koobro-0.0.11.dist-info/LICENSE
koobro-0.0.11.dist-info/METADATA
koobro-0.0.11.dist-info/WHEEL
koobro-0.0.11.dist-info/top_level.txt
koobro-0.0.11.dist-info/RECORD
